cemu/__init__.py
cemu/__main__.py
cemu/const.py
cemu/core.py
cemu/emulator.py
cemu/errors.py
cemu/exceptions.py
cemu/exports.py
cemu/log.py
cemu/memory.py
cemu/os.py
cemu/settings.py
cemu/shortcuts.py
cemu/utils.py
cemu/arch/__init__.py
cemu/arch/arm.py
cemu/arch/generic.py
cemu/arch/mips.py
cemu/arch/ppc.py
cemu/arch/sparc.py
cemu/arch/x86.py
cemu/cli/__init__.py
cemu/cli/repl.py
cemu/examples/aarch64_sys_exec_bin_sh.asm
cemu/examples/arm_nops.raw
cemu/examples/arm_sys_exec_bin_sh.asm
cemu/examples/mips_sys_exec_bin_sh.asm
cemu/examples/mipsbe_sys_exec_bin_sh.asm
cemu/examples/sparc64_sys_exec_bin_sh.asm
cemu/examples/sparc_nops.raw
cemu/examples/sparc_sys_exec_bin_sh.asm
cemu/examples/x86_32_read_flag_null_free.asm
cemu/examples/x86_32_sys_exec_bin_sh.asm
cemu/examples/x86_32_sys_exec_bin_sh_null_free.asm
cemu/examples/x86_64_read_flag_null_free.asm
cemu/examples/x86_64_sys_exec_bin_sh.asm
cemu/examples/x86_64_sys_exec_bin_sh_null_free.asm
cemu/examples/x86_nops.raw
cemu/img/cemu-windows-dark.png
cemu/img/cemu-windows-light.png
cemu/img/icon.png
cemu/img/new_logo.png
cemu/plugins/__init__.py
cemu/plugins/scratchboard.py
cemu/plugins/pyconsole/__init__.py
cemu/plugins/pyconsole/console.py
cemu/styles/default.qss
cemu/syscalls/linux/aarch64.csv
cemu/syscalls/linux/arm-thumb.csv
cemu/syscalls/linux/arm.csv
cemu/syscalls/linux/mips.csv
cemu/syscalls/linux/mips64.csv
cemu/syscalls/linux/sparc.csv
cemu/syscalls/linux/x86-64.csv
cemu/syscalls/linux/x86.csv
cemu/templates/about.html
cemu/templates/cemu.ini
cemu/templates/linux/template.asm
cemu/templates/linux/template.c
cemu/ui/__init__.py
cemu/ui/codeeditor.py
cemu/ui/command.py
cemu/ui/highlighter.py
cemu/ui/log.py
cemu/ui/main.py
cemu/ui/mapping.py
cemu/ui/memory.py
cemu/ui/registers.py
cemu/ui/utils.py
cemu-0.8.0.dist-info/METADATA
cemu-0.8.0.dist-info/WHEEL
cemu-0.8.0.dist-info/entry_points.txt
cemu-0.8.0.dist-info/licenses/LICENSE
cemu-0.8.0.dist-info/RECORD
