Metadata-Version: 2.3
Name: CEmu
Version: 0.8.0
Summary: Cemu is a simple assembly/dissembly/emulation IDE that provides an easy Plug-n-Play environment to start playing with many architectures (currently supports x86-{32,64}, ARM, AARCH64, MIPS, MIPS64, SPARC and PPC).
Project-URL: Homepage, https://github.com/hugsy/cemu
Project-URL: Bug Tracker, https://github.com/hugsy/cemu/issues
Author-email: hugsy <hugsy@blah.cat>
License-File: LICENSE
Keywords: aarch64,arm,assembly,disassembly,emulation,mips,powerpc,sparc,x64,x86
Classifier: Development Status :: 4 - Beta
Classifier: Environment :: Console
Classifier: License :: OSI Approved :: MIT License
Classifier: Natural Language :: English
Classifier: Programming Language :: Python :: 3 :: Only
Classifier: Programming Language :: Python :: 3.10
Classifier: Topic :: Software Development :: Assemblers
Requires-Python: >=3.10
Requires-Dist: capstone>=5.0.1
Requires-Dist: keystone-engine>=0.9.2
Requires-Dist: lief>=0.15.1
Requires-Dist: loguru>=0.7.2
Requires-Dist: prompt-toolkit>=3.0.47
Requires-Dist: pygments>=2.18.0
Requires-Dist: pyqt6>=6.7.1
Requires-Dist: setuptools>=72.1.0
Requires-Dist: unicorn>=2.0.1.post1
